thoughtspot_tml/__init__.py
thoughtspot_tml/__project__.py
thoughtspot_tml/_compat.py
thoughtspot_tml/_scriptability.py
thoughtspot_tml/_tml.py
thoughtspot_tml/_yaml.py
thoughtspot_tml/exceptions.py
thoughtspot_tml/spotapp.py
thoughtspot_tml/tml.py
thoughtspot_tml/types.py
thoughtspot_tml/utils.py
thoughtspot_tml-2.4.2.dist-info/METADATA
thoughtspot_tml-2.4.2.dist-info/WHEEL
thoughtspot_tml-2.4.2.dist-info/licenses/LICENSE
thoughtspot_tml-2.4.2.dist-info/RECORD
