Metadata-Version: 2.4
Name: thoughtspot_tml
Version: 2.4.2
Summary: Library for manipulating ThoughtSpot Modeling Language (TML) files
Project-URL: repository, https://github.com/thoughtspot/thoughtspot_tml
Project-URL: bug_tracker, https://github.com/thoughtspot/thoughtspot_tml/issues
Author-email: Bryant Howell <bryant.howell@thoughtspot.com>, Bill B <bill.back@thoughtspot.com>, boonhapus <nicholas.cooper@thoughtspot.com>
Maintainer-email: Bryant Howell <bryant.howell@thoughtspot.com>, boonhapus <nicholas.cooper@thoughtspot.com>
License: #ThoughtSpot Development Tools End User License Agreement
License-File: LICENSE
Classifier: Intended Audience :: Developers
Classifier: License :: Other/Proprietary License
Classifier: Operating System :: OS Independent
Classifier: Programming Language :: Python :: 3 :: Only
Classifier: Programming Language :: Python :: 3.9
Classifier: Programming Language :: Python :: 3.10
Classifier: Programming Language :: Python :: 3.11
Classifier: Programming Language :: Python :: 3.12
Classifier: Programming Language :: Python :: 3.13
Requires-Python: <3.14,>=3.9
Requires-Dist: betterproto[compiler]==2.0.0b6
Requires-Dist: pyyaml>=6.0.0
Requires-Dist: typing-extensions>=4.4.0; python_version < '3.11.0'
Requires-Dist: zipp>=3.11.0; python_version < '3.10.0'
Provides-Extra: dev
Requires-Dist: coverage[toml]; extra == 'dev'
Requires-Dist: hatch; extra == 'dev'
Requires-Dist: mypy; extra == 'dev'
Requires-Dist: nox; extra == 'dev'
Requires-Dist: pre-commit; extra == 'dev'
Requires-Dist: rich; extra == 'dev'
Requires-Dist: ruff; extra == 'dev'
Requires-Dist: types-pyyaml; extra == 'dev'
Requires-Dist: vulture; extra == 'dev'
Requires-Dist: ward; extra == 'dev'
